respan_exporter_agno/__init__.py
respan_exporter_agno/exporter.py
respan_exporter_agno/instrumentor.py
respan_exporter_agno-1.0.0.dist-info/METADATA
respan_exporter_agno-1.0.0.dist-info/WHEEL
respan_exporter_agno-1.0.0.dist-info/RECORD
