Metadata-Version: 2.1
Name: respan-exporter-agno
Version: 1.0.0
Summary: Respan exporter for Agno traces
Author: Respan
Author-email: team@respan.ai
Requires-Python: >=3.12,<3.15
Classifier: Programming Language :: Python :: 3
Classifier: Programming Language :: Python :: 3.12
Requires-Dist: opentelemetry-api (>=1.20.0,<2.0.0)
Requires-Dist: opentelemetry-instrumentation (>=0.41b0,<0.42)
Requires-Dist: opentelemetry-sdk (>=1.20.0,<2.0.0)
Requires-Dist: requests (>=2.32.5,<3.0.0)
Requires-Dist: wrapt (>=1.16.0,<2.0.0)
